{
	"configurations" : 
	[
		{
			"directories" : 
			[
				{
					"build" : ".",
					"jsonFile" : "directory-.-Debug-f5ebdc15457944623624.json",
					"minimumCMakeVersion" : 
					{
						"string" : "3.24"
					},
					"projectIndex" : 0,
					"source" : ".",
					"targetIndexes" : 
					[
						0
					]
				}
			],
			"name" : "Debug",
			"projects" : 
			[
				{
					"directoryIndexes" : 
					[
						0
					],
					"name" : "LRU_Cach_CPP",
					"targetIndexes" : 
					[
						0
					]
				}
			],
			"targets" : 
			[
				{
					"directoryIndex" : 0,
					"id" : "LRU_Cach_CPP::@6890427a1f51a3e7e1df",
					"jsonFile" : "target-LRU_Cach_CPP-Debug-514742e0c71c65440d15.json",
					"name" : "LRU_Cach_CPP",
					"projectIndex" : 0
				}
			]
		}
	],
	"kind" : "codemodel",
	"paths" : 
	{
		"build" : "/home/yelnat/Documents/programmin/leetcode/LRU_Cach_CPP/cmake-build-debug",
		"source" : "/home/yelnat/Documents/programmin/leetcode/LRU_Cach_CPP"
	},
	"version" : 
	{
		"major" : 2,
		"minor" : 4
	}
}
